iXBRLViewerPlugin/__init__.py
iXBRLViewerPlugin/_version.py
iXBRLViewerPlugin/constants.py
iXBRLViewerPlugin/featureConfig.py
iXBRLViewerPlugin/iXBRLViewer.py
iXBRLViewerPlugin/plugin.py
iXBRLViewerPlugin/stubviewer.html
iXBRLViewerPlugin/ui.py
iXBRLViewerPlugin/xhtmlserialize.py
iXBRLViewerPlugin/viewer/i18next-parser.config.js
iXBRLViewerPlugin/viewer/version.js
iXBRLViewerPlugin/viewer/webpack.common.js
iXBRLViewerPlugin/viewer/webpack.dev.js
iXBRLViewerPlugin/viewer/webpack.prod.js
iXBRLViewerPlugin/viewer/dist/ixbrlviewer.js
iXBRLViewerPlugin/viewer/dist/ixbrlviewer.js.LICENSE.txt
iXBRLViewerPlugin/viewer/src/data/utr.json
iXBRLViewerPlugin/viewer/src/html/fact-details.html
iXBRLViewerPlugin/viewer/src/html/footer-logo.html
iXBRLViewerPlugin/viewer/src/html/footnote-details.html
iXBRLViewerPlugin/viewer/src/html/inspector.html
iXBRLViewerPlugin/viewer/src/i18n/cy/balancetypes.json
iXBRLViewerPlugin/viewer/src/i18n/cy/currencies.json
iXBRLViewerPlugin/viewer/src/i18n/cy/datatypes.json
iXBRLViewerPlugin/viewer/src/i18n/cy/labelroles.json
iXBRLViewerPlugin/viewer/src/i18n/cy/referenceparts.json
iXBRLViewerPlugin/viewer/src/i18n/cy/scale.json
iXBRLViewerPlugin/viewer/src/i18n/cy/tooltips.json
iXBRLViewerPlugin/viewer/src/i18n/cy/translation.json
iXBRLViewerPlugin/viewer/src/i18n/da/balancetypes.json
iXBRLViewerPlugin/viewer/src/i18n/da/currencies.json
iXBRLViewerPlugin/viewer/src/i18n/da/datatypes.json
iXBRLViewerPlugin/viewer/src/i18n/da/labelroles.json
iXBRLViewerPlugin/viewer/src/i18n/da/referenceparts.json
iXBRLViewerPlugin/viewer/src/i18n/da/scale.json
iXBRLViewerPlugin/viewer/src/i18n/da/tooltips.json
iXBRLViewerPlugin/viewer/src/i18n/da/translation.json
iXBRLViewerPlugin/viewer/src/i18n/de/balancetypes.json
iXBRLViewerPlugin/viewer/src/i18n/de/currencies.json
iXBRLViewerPlugin/viewer/src/i18n/de/datatypes.json
iXBRLViewerPlugin/viewer/src/i18n/de/labelroles.json
iXBRLViewerPlugin/viewer/src/i18n/de/referenceparts.json
ixbrl_viewer-1.4.85.dist-info/licenses/LICENSE.md
ixbrl_viewer-1.4.85.dist-info/licenses/NOTICE
ixbrl_viewer-1.4.85.dist-info/METADATA
ixbrl_viewer-1.4.85.dist-info/WHEEL
ixbrl_viewer-1.4.85.dist-info/entry_points.txt
ixbrl_viewer-1.4.85.dist-info/top_level.txt
ixbrl_viewer-1.4.85.dist-info/RECORD
