Metadata-Version: 2.4
Name: ixbrl-viewer
Version: 1.4.85
Summary: The Arelle iXBRL Viewer allows iXBRL reports to be viewed interactively in a web browser.
Author-email: "arelle.org" <support@arelle.org>
License-Expression: Apache-2.0
Project-URL: Homepage, https://arelle.org/
Project-URL: Downloads, https://arelle.org/arelle/pub/
Project-URL: Documentation, https://arelle.org/arelle/documentation/
Project-URL: Blog, https://arelle.org/arelle/blog/
Project-URL: Source Code, https://github.com/Arelle/ixbrl-viewer
Project-URL: Bug Reports, https://github.com/Arelle/ixbrl-viewer/issues/
Project-URL: Support, https://groups.google.com/g/arelle-users/
Keywords: arelle,plugin,xbrl
Platform: any
Classifier: Development Status :: 5 - Production/Stable
Classifier: Intended Audience :: End Users/Desktop
Classifier: Intended Audience :: Developers
Classifier: Natural Language :: English
Classifier: Programming Language :: Python :: 3
Classifier: Programming Language :: Python :: 3.10
Classifier: Programming Language :: Python :: 3.11
Classifier: Programming Language :: Python :: 3.12
Classifier: Programming Language :: Python :: 3.13
Classifier: Programming Language :: Python :: 3.14
Classifier: Operating System :: OS Independent
Classifier: Topic :: Text Processing :: Markup :: XML
Requires-Python: >=3.10
License-File: LICENSE.md
License-File: NOTICE
Requires-Dist: bottle<0.14,>=0.13
Requires-Dist: lxml<7,>=4
Provides-Extra: arelle
Requires-Dist: arelle_release==2.*; extra == "arelle"
Provides-Extra: dev
Requires-Dist: flake8==7.3.0; extra == "dev"
Requires-Dist: mypy==1.19.1; extra == "dev"
Requires-Dist: pytest==9.0.2; extra == "dev"
Requires-Dist: types-lxml==2026.1.1; extra == "dev"
Requires-Dist: typing-extensions==4.15.0; extra == "dev"
Dynamic: license-file
